timod/__init__.py
timod/taichi_kernel_module.py
timod-0.0.17.dist-info/LICENSE
timod-0.0.17.dist-info/METADATA
timod-0.0.17.dist-info/WHEEL
timod-0.0.17.dist-info/top_level.txt
timod-0.0.17.dist-info/RECORD
