Metadata-Version: 2.1
Name: timod
Version: 0.0.17
Summary: A PyTorch module wrapper for Taichi kernels
Home-page: https://github.com/Kiord/timod
Author: Kiord
Author-email: glenn.kerbiriou@gmail.com
License: UNKNOWN
Project-URL: Source, https://github.com/Kiord/timod
Project-URL: Tracker, https://github.com/Kiord/timod/issues
Platform: UNKNOWN
Classifier: Programming Language :: Python :: 3
Classifier: License :: OSI Approved :: MIT License
Classifier: Operating System :: OS Independent
Requires-Python: >=3.7
Requires-Dist: torch>=2.0
Requires-Dist: taichi>=1.6
